[
    {
        "inputs": [
            {
                "internalType": "address",
                "name": "_selfProtocolVerifier",
                "type": "address"
            },
            {
                "internalType": "address",
                "name": "_cUSD",
                "type": "address"
            },
            {
                "internalType": "address",
                "name": "_feeCollector",
                "type": "address"
            },
            {
                "internalType": "uint256",
                "name": "_registrationFee",
                "type": "uint256"
            }
        ],
        "stateMutability": "nonpayable",
        "type": "constructor"
    },
    {
        "inputs": [],
        "name": "ECDSAInvalidSignature",
        "type": "error"
    },
    {
        "inputs": [
            {
                "internalType": "uint256",
                "name": "length",
                "type": "uint256"
            }
        ],
        "name": "ECDSAInvalidSignatureLength",
        "type": "error"
    },
    {
        "inputs": [
            {
                "internalType": "bytes32",
                "name": "s",
                "type": "bytes32"
            }
        ],
        "name": "ECDSAInvalidSignatureS",
        "type": "error"
    },
    {
        "inputs": [],
        "name": "ReentrancyGuardReentrantCall",
        "type": "error"
    },
    {
        "anonymous": false,
        "inputs": [
            {
                "indexed": true,
                "internalType": "address",
                "name": "ngo",
                "type": "address"
            },
            {
                "indexed": true,
                "internalType": "address",
                "name": "donor",
                "type": "address"
            },
            {
                "indexed": false,
                "internalType": "uint256",
                "name": "amount",
                "type": "uint256"
            }
        ],
        "name": "DonationRecorded",
        "type": "event"
    },
    {
        "anonymous": false,
        "inputs": [
            {
                "indexed": false,
                "internalType": "address",
                "name": "oldCollector",
                "type": "address"
            },
            {
                "indexed": false,
                "internalType": "address",
                "name": "newCollector",
                "type": "address"
            }
        ],
        "name": "FeeCollectorUpdated",
        "type": "event"
    },
    {
        "anonymous": false,
        "inputs": [
            {
                "indexed": true,
                "internalType": "address",
                "name": "ngo",
                "type": "address"
            },
            {
                "indexed": true,
                "internalType": "address",
                "name": "challenger",
                "type": "address"
            },
            {
                "indexed": false,
                "internalType": "string",
                "name": "reason",
                "type": "string"
            },
            {
                "indexed": false,
                "internalType": "uint256",
                "name": "challengeCount",
                "type": "uint256"
            }
        ],
        "name": "NGOChallenged",
        "type": "event"
    },
    {
        "anonymous": false,
        "inputs": [
            {
                "indexed": true,
                "internalType": "address",
                "name": "ngoWallet",
                "type": "address"
            },
            {
                "indexed": false,
                "internalType": "string",
                "name": "newIpfsHash",
                "type": "string"
            }
        ],
        "name": "NGOProfileUpdated",
        "type": "event"
    },
    {
        "anonymous": false,
        "inputs": [
            {
                "indexed": true,
                "internalType": "address",
                "name": "ngoWallet",
                "type": "address"
            },
            {
                "indexed": false,
                "internalType": "string",
                "name": "founderDID",
                "type": "string"
            },
            {
                "indexed": false,
                "internalType": "string",
                "name": "country",
                "type": "string"
            },
            {
                "indexed": false,
                "internalType": "uint256",
                "name": "timestamp",
                "type": "uint256"
            }
        ],
        "name": "NGORegistered",
        "type": "event"
    },
    {
        "anonymous": false,
        "inputs": [
            {
                "indexed": true,
                "internalType": "address",
                "name": "ngo",
                "type": "address"
            },
            {
                "indexed": false,
                "internalType": "string",
                "name": "reason",
                "type": "string"
            }
        ],
        "name": "NGORevoked",
        "type": "event"
    },
    {
        "anonymous": false,
        "inputs": [
            {
                "indexed": false,
                "internalType": "uint256",
                "name": "oldFee",
                "type": "uint256"
            },
            {
                "indexed": false,
                "internalType": "uint256",
                "name": "newFee",
                "type": "uint256"
            }
        ],
        "name": "RegistrationFeeUpdated",
        "type": "event"
    },
    {
        "anonymous": false,
        "inputs": [
            {
                "indexed": false,
                "internalType": "address",
                "name": "oldVerifier",
                "type": "address"
            },
            {
                "indexed": false,
                "internalType": "address",
                "name": "newVerifier",
                "type": "address"
            }
        ],
        "name": "SelfProtocolVerifierUpdated",
        "type": "event"
    },
    {
        "inputs": [],
        "name": "CHALLENGE_THRESHOLD",
        "outputs": [
            {
                "internalType": "uint256",
                "name": "",
                "type": "uint256"
            }
        ],
        "stateMutability": "view",
        "type": "function"
    },
    {
        "inputs": [],
        "name": "admin",
        "outputs": [
            {
                "internalType": "address",
                "name": "",
                "type": "address"
            }
        ],
        "stateMutability": "view",
        "type": "function"
    },
    {
        "inputs": [
            {
                "internalType": "address",
                "name": "_ngo",
                "type": "address"
            },
            {
                "internalType": "string",
                "name": "_reason",
                "type": "string"
            }
        ],
        "name": "adminRevokeNGO",
        "outputs": [],
        "stateMutability": "nonpayable",
        "type": "function"
    },
    {
        "inputs": [],
        "name": "cUSD",
        "outputs": [
            {
                "internalType": "contract IERC20",
                "name": "",
                "type": "address"
            }
        ],
        "stateMutability": "view",
        "type": "function"
    },
    {
        "inputs": [
            {
                "internalType": "address",
                "name": "",
                "type": "address"
            }
        ],
        "name": "challengeCount",
        "outputs": [
            {
                "internalType": "uint256",
                "name": "",
                "type": "uint256"
            }
        ],
        "stateMutability": "view",
        "type": "function"
    },
    {
        "inputs": [
            {
                "internalType": "address",
                "name": "_ngo",
                "type": "address"
            },
            {
                "internalType": "string",
                "name": "_reason",
                "type": "string"
            }
        ],
        "name": "challengeNGO",
        "outputs": [],
        "stateMutability": "nonpayable",
        "type": "function"
    },
    {
        "inputs": [],
        "name": "feeCollector",
        "outputs": [
            {
                "internalType": "address",
                "name": "",
                "type": "address"
            }
        ],
        "stateMutability": "view",
        "type": "function"
    },
    {
        "inputs": [],
        "name": "getAllVerifiedNGOs",
        "outputs": [
            {
                "internalType": "address[]",
                "name": "",
                "type": "address[]"
            }
        ],
        "stateMutability": "view",
        "type": "function"
    },
    {
        "inputs": [
            {
                "internalType": "address",
                "name": "_ngo",
                "type": "address"
            }
        ],
        "name": "getNGO",
        "outputs": [
            {
                "components": [
                    {
                        "internalType": "string",
                        "name": "founderDID",
                        "type": "string"
                    },
                    {
                        "internalType": "bytes32",
                        "name": "vcProofHash",
                        "type": "bytes32"
                    },
                    {
                        "internalType": "uint8",
                        "name": "founderAge",
                        "type": "uint8"
                    },
                    {
                        "internalType": "string",
                        "name": "founderCountry",
                        "type": "string"
                    },
                    {
                        "internalType": "address",
                        "name": "ngoWallet",
                        "type": "address"
                    },
                    {
                        "internalType": "string",
                        "name": "ipfsProfile",
                        "type": "string"
                    },
                    {
                        "internalType": "uint256",
                        "name": "registeredAt",
                        "type": "uint256"
                    },
                    {
                        "internalType": "uint256",
                        "name": "vcExpiryDate",
                        "type": "uint256"
                    },
                    {
                        "internalType": "bool",
                        "name": "isActive",
                        "type": "bool"
                    },
                    {
                        "internalType": "uint256",
                        "name": "totalDonationsReceived",
                        "type": "uint256"
                    },
                    {
                        "internalType": "uint256",
                        "name": "donorCount",
                        "type": "uint256"
                    }
                ],
                "internalType": "struct NGORegistry.NGO",
                "name": "",
                "type": "tuple"
            }
        ],
        "stateMutability": "view",
        "type": "function"
    },
    {
        "inputs": [
            {
                "internalType": "string",
                "name": "_countryCode",
                "type": "string"
            }
        ],
        "name": "getNGOsByCountry",
        "outputs": [
            {
                "internalType": "address[]",
                "name": "",
                "type": "address[]"
            }
        ],
        "stateMutability": "view",
        "type": "function"
    },
    {
        "inputs": [],
        "name": "getTotalVerifiedNGOs",
        "outputs": [
            {
                "internalType": "uint256",
                "name": "",
                "type": "uint256"
            }
        ],
        "stateMutability": "view",
        "type": "function"
    },
    {
        "inputs": [
            {
                "internalType": "address",
                "name": "",
                "type": "address"
            },
            {
                "internalType": "address",
                "name": "",
                "type": "address"
            }
        ],
        "name": "hasChallenger",
        "outputs": [
            {
                "internalType": "bool",
                "name": "",
                "type": "bool"
            }
        ],
        "stateMutability": "view",
        "type": "function"
    },
    {
        "inputs": [
            {
                "internalType": "address",
                "name": "_ngo",
                "type": "address"
            }
        ],
        "name": "isVCExpired",
        "outputs": [
            {
                "internalType": "bool",
                "name": "",
                "type": "bool"
            }
        ],
        "stateMutability": "view",
        "type": "function"
    },
    {
        "inputs": [
            {
                "internalType": "address",
                "name": "_ngo",
                "type": "address"
            }
        ],
        "name": "isVerified",
        "outputs": [
            {
                "internalType": "bool",
                "name": "",
                "type": "bool"
            }
        ],
        "stateMutability": "view",
        "type": "function"
    },
    {
        "inputs": [
            {
                "internalType": "address",
                "name": "",
                "type": "address"
            }
        ],
        "name": "ngoByWallet",
        "outputs": [
            {
                "internalType": "string",
                "name": "founderDID",
                "type": "string"
            },
            {
                "internalType": "bytes32",
                "name": "vcProofHash",
                "type": "bytes32"
            },
            {
                "internalType": "uint8",
                "name": "founderAge",
                "type": "uint8"
            },
            {
                "internalType": "string",
                "name": "founderCountry",
                "type": "string"
            },
            {
                "internalType": "address",
                "name": "ngoWallet",
                "type": "address"
            },
            {
                "internalType": "string",
                "name": "ipfsProfile",
                "type": "string"
            },
            {
                "internalType": "uint256",
                "name": "registeredAt",
                "type": "uint256"
            },
            {
                "internalType": "uint256",
                "name": "vcExpiryDate",
                "type": "uint256"
            },
            {
                "internalType": "bool",
                "name": "isActive",
                "type": "bool"
            },
            {
                "internalType": "uint256",
                "name": "totalDonationsReceived",
                "type": "uint256"
            },
            {
                "internalType": "uint256",
                "name": "donorCount",
                "type": "uint256"
            }
        ],
        "stateMutability": "view",
        "type": "function"
    },
    {
        "inputs": [
            {
                "internalType": "address",
                "name": "_ngo",
                "type": "address"
            },
            {
                "internalType": "address",
                "name": "_donor",
                "type": "address"
            },
            {
                "internalType": "uint256",
                "name": "_amount",
                "type": "uint256"
            }
        ],
        "name": "recordDonation",
        "outputs": [],
        "stateMutability": "nonpayable",
        "type": "function"
    },
    {
        "inputs": [
            {
                "internalType": "string",
                "name": "_founderDID",
                "type": "string"
            },
            {
                "internalType": "bytes32",
                "name": "_vcProofHash",
                "type": "bytes32"
            },
            {
                "internalType": "bytes",
                "name": "_vcSignature",
                "type": "bytes"
            },
            {
                "internalType": "uint8",
                "name": "_founderAge",
                "type": "uint8"
            },
            {
                "internalType": "string",
                "name": "_founderCountry",
                "type": "string"
            },
            {
                "internalType": "string",
                "name": "_ipfsProfile",
                "type": "string"
            },
            {
                "internalType": "uint256",
                "name": "_vcExpiryDate",
                "type": "uint256"
            }
        ],
        "name": "registerNGO",
        "outputs": [],
        "stateMutability": "nonpayable",
        "type": "function"
    },
    {
        "inputs": [],
        "name": "registrationFee",
        "outputs": [
            {
                "internalType": "uint256",
                "name": "",
                "type": "uint256"
            }
        ],
        "stateMutability": "view",
        "type": "function"
    },
    {
        "inputs": [],
        "name": "selfProtocolVerifier",
        "outputs": [
            {
                "internalType": "address",
                "name": "",
                "type": "address"
            }
        ],
        "stateMutability": "view",
        "type": "function"
    },
    {
        "inputs": [
            {
                "internalType": "address",
                "name": "_newAdmin",
                "type": "address"
            }
        ],
        "name": "transferAdmin",
        "outputs": [],
        "stateMutability": "nonpayable",
        "type": "function"
    },
    {
        "inputs": [
            {
                "internalType": "address",
                "name": "_newCollector",
                "type": "address"
            }
        ],
        "name": "updateFeeCollector",
        "outputs": [],
        "stateMutability": "nonpayable",
        "type": "function"
    },
    {
        "inputs": [
            {
                "internalType": "string",
                "name": "_newIpfsHash",
                "type": "string"
            }
        ],
        "name": "updateProfile",
        "outputs": [],
        "stateMutability": "nonpayable",
        "type": "function"
    },
    {
        "inputs": [
            {
                "internalType": "uint256",
                "name": "_newFee",
                "type": "uint256"
            }
        ],
        "name": "updateRegistrationFee",
        "outputs": [],
        "stateMutability": "nonpayable",
        "type": "function"
    },
    {
        "inputs": [
            {
                "internalType": "address",
                "name": "_newVerifier",
                "type": "address"
            }
        ],
        "name": "updateSelfProtocolVerifier",
        "outputs": [],
        "stateMutability": "nonpayable",
        "type": "function"
    },
    {
        "inputs": [
            {
                "internalType": "bytes32",
                "name": "",
                "type": "bytes32"
            }
        ],
        "name": "usedVCProofs",
        "outputs": [
            {
                "internalType": "bool",
                "name": "",
                "type": "bool"
            }
        ],
        "stateMutability": "view",
        "type": "function"
    },
    {
        "inputs": [
            {
                "internalType": "uint256",
                "name": "",
                "type": "uint256"
            }
        ],
        "name": "verifiedNGOs",
        "outputs": [
            {
                "internalType": "address",
                "name": "",
                "type": "address"
            }
        ],
        "stateMutability": "view",
        "type": "function"
    },
    {
        "inputs": [
            {
                "internalType": "string",
                "name": "",
                "type": "string"
            }
        ],
        "name": "walletByDID",
        "outputs": [
            {
                "internalType": "address",
                "name": "",
                "type": "address"
            }
        ],
        "stateMutability": "view",
        "type": "function"
    }
]